pysyscontrol/Diffeq.py
pysyscontrol/PDiffeq.py
pysyscontrol/__init__.py
pysyscontrol/Control/__init__.py
pysyscontrol/Control/laplace_handler.py
pysyscontrol/Control/plotting.py
pysyscontrol/Control/transfer_function.py
pysyscontrol/ODE/__init__.py
pysyscontrol/ODE/solver.py
pysyscontrol/PDE/__init__.py
pysyscontrol/PDE/oned_wavefunction.py
pysyscontrol/PDE/tem.py
pysyscontrol/PDE/wave.py
pysyscontrol/Quantum/__init__.py
pysyscontrol/Quantum/grape/__init__.py
pysyscontrol/Quantum/grape/bloch.py
pysyscontrol/Quantum/grape/fidelity.py
pysyscontrol/Quantum/grape/grape.py
pysyscontrol/Quantum/grape/hamiltonians.py
pysyscontrol/Quantum/grape/optimizers.py
pysyscontrol/Quantum/grape/pulse_solvers.py
pysyscontrol/Quantum/grape/utils.py
pysyscontrol/Quantum/grover/__init__.py
pysyscontrol/Quantum/grover/diffuser.py
pysyscontrol/Quantum/grover/grover_solver.py
pysyscontrol/Quantum/grover/groversearch.py
pysyscontrol/Quantum/grover/oracle.py
pysyscontrol/Quantum/grover/utils.py
pysyscontrol/Quantum/grover/visualize.py
pysyscontrol-2.0.2.dist-info/METADATA
pysyscontrol-2.0.2.dist-info/WHEEL
pysyscontrol-2.0.2.dist-info/top_level.txt
pysyscontrol-2.0.2.dist-info/RECORD
