Metadata-Version: 2.4
Name: pysyscontrol
Version: 2.0.2
Summary: A Python package for Control Systems Analysis
Home-page: https://github.com/Shagedoorn1/PySysControl
Author: Shagedoorn1
Author-email: svenhagedoorn@gmail.com
Classifier: Programming Language :: Python :: 3
Classifier: License :: OSI Approved :: MIT License
Classifier: Operating System :: OS Independent
Requires-Python: >=3.12
Requires-Dist: numpy>=1.26
Requires-Dist: matplotlib>=3.7
Requires-Dist: sympy>=1.12
Requires-Dist: scipy>=1.11
Dynamic: author
Dynamic: author-email
Dynamic: classifier
Dynamic: description
Dynamic: description-content-type
Dynamic: home-page
Dynamic: requires-dist
Dynamic: requires-python
Dynamic: summary
